sphinx_tutorials/__init__.py
sphinx_tutorials/_version.py
sphinx_tutorials/ext.py
sphinx_tutorials/sphinx_tutorials.py
sphinx_tutorials/_docs_files/_static/st-base.css
sphinx_tutorials/_docs_files/_static/st-code-copybotton-old-good.js
sphinx_tutorials/_docs_files/_static/st-code-copybotton.css
sphinx_tutorials/_docs_files/_static/st-code-copybotton.js
sphinx_tutorials/_docs_files/_static/st-code-ipythonprompt.js
sphinx_tutorials/_docs_files/_static/st-code.css
sphinx_tutorials/_docs_files/_static/st-nav-bar.css
sphinx_tutorials/_docs_files/_static/st-overloads.css
sphinx_tutorials/_docs_files/_static/st-page.js
sphinx_tutorials/_docs_files/_static/st-tab-set.css
sphinx_tutorials/_docs_files/_static/st-table-rst.css
sphinx_tutorials/_docs_files/_static/_st-unused/st-bullets.css
sphinx_tutorials/_docs_files/_static/_st-unused/st-extra-squares.css
sphinx_tutorials/_docs_files/_static/_st-unused/st-jupyter-notebooks.css
sphinx_tutorials/_docs_files/_static/_st-unused/st-jupyter-notebooks.js
sphinx_tutorials/other_extensions/__init__.py
sphinx_tutorials/other_extensions/autodoc_ext.py
sphinx_tutorials/other_extensions/sig_shaper/__init__.py
sphinx_tutorials/other_extensions/sig_shaper/_paguro_.py
sphinx_tutorials/other_extensions/sig_shaper/sig_shaper.py
sphinx_tutorials/utils/__init__.py
sphinx_tutorials/utils/copy.py
sphinx_tutorials/utils/py_rules.py
sphinx_tutorials/utils/table_tree.py
sphinx_tutorials/utils/toc_tree.py
sphinx_tutorials-0.0.8.dist-info/licenses/LICENSE
sphinx_tutorials-0.0.8.dist-info/METADATA
sphinx_tutorials-0.0.8.dist-info/WHEEL
sphinx_tutorials-0.0.8.dist-info/entry_points.txt
sphinx_tutorials-0.0.8.dist-info/top_level.txt
sphinx_tutorials-0.0.8.dist-info/RECORD
