Metadata-Version: 2.4
Name: sphinx_tutorials
Version: 0.0.8
Summary: Tools for docs in Python
Author-email: Bernardo Dionisi <bernardo.dionisi@gmail.com>
License:                                 Apache License
Project-URL: Homepage, https://github.com/bernardodionisi/sphinx_tutorials
Project-URL: Source, https://github.com/bernardodionisi/sphinx_tutorials
Project-URL: Issues, https://github.com/bernardodionisi/sphinx_tutorials/issues
Project-URL: Documentation, https://bernardodionisi.github.io/sphinx_tutorials/latest/
Keywords: tools for docs
Classifier: Intended Audience :: Science/Research
Classifier: Intended Audience :: Education
Classifier: Intended Audience :: Developers
Classifier: Topic :: Software Development :: Libraries :: Python Modules
Classifier: License :: OSI Approved :: Apache Software License
Classifier: Programming Language :: Python :: 3.10
Classifier: Programming Language :: Python :: 3.11
Classifier: Programming Language :: Python :: 3.12
Classifier: Programming Language :: Python :: 3.13
Classifier: Programming Language :: Python :: 3.14
Classifier: Operating System :: OS Independent
Requires-Python: >=3.10
License-File: LICENSE
Requires-Dist: sphinx==8.2.3
Requires-Dist: sphinx-immaterial==0.13.6
Requires-Dist: myst-parser==4.0.0
Requires-Dist: ipykernel==6.26.0
Requires-Dist: sphinx_design
Requires-Dist: typing_extensions>=4.0.0
Provides-Extra: dev-test
Requires-Dist: pytest; extra == "dev-test"
Requires-Dist: pytest-cov[toml]; extra == "dev-test"
Requires-Dist: pytest-xdist; extra == "dev-test"
Requires-Dist: pytest-benchmark>=4.0.0; extra == "dev-test"
Provides-Extra: dev-typing
Requires-Dist: mypy; extra == "dev-typing"
Provides-Extra: dev-lint
Requires-Dist: ruff; extra == "dev-lint"
Provides-Extra: docs
Dynamic: license-file
